{
  "NewWorldGameWindowDimensions": null,
  "RawPriceData": [
    {
      "ItemName": "Life Mote",
      "Price": "167",
      "Tier": "II",
      "GearScore": "7",
      "Availability": "709",
      "Location": "Everfall"
    },
    {
      "ItemName": "Life Mote",
      "Price": "167",
      "Tier": "II",
      "GearScore": "2",
      "Availability": "101",
      "Location": "First Light"
    },
    {
      "ItemName": "Life Mote",
      "Price": "168",
      "Tier": "II",
      "GearScore": "1",
      "Availability": "63",
      "Location": "Everfall"
    },
    {
      "ItemName": "Life Mote",
      "Price": "169",
      "Tier": "II",
      "GearScore": "",
      "Availability": "194",
      "Location": "Windsward"
    },
    {
      "ItemName": "Life Mote",
      "Price": "169",
      "Tier": "II",
      "GearScore": "7",
      "Availability": "13",
      "Location": "Everfall"
    },
    {
      "ItemName": "Life Mote",
      "Price": "179",
      "Tier": "II",
      "GearScore": "5",
      "Availability": "439",
      "Location": "Reekwater"
    },
    {
      "ItemName": "Life Mote",
      "Price": "180",
      "Tier": "II",
      "GearScore": "7",
      "Availability": "824",
      "Location": "Windsward"
    },
    {
      "ItemName": "Life Mote",
      "Price": "180",
      "Tier": "II",
      "GearScore": "7",
      "Availability": "106",
      "Location": "Windsward"
    },
    {
      "ItemName": "Life Mote",
      "Price": "183",
      "Tier": "II",
      "GearScore": "7",
      "Availability": "25",
      "Location": "Mourningdale"
    },
    {
      "ItemName": "1 e Mata",
      "Price": "1",
      "Tier": "",
      "GearScore": "7",
      "Availability": "1 2 9",
      "Location": "Wineeward"
    },
    {
      "ItemName": "Mate",
      "Price": "15",
      "Tier": "",
      "GearScore": "7",
      "Availability": "14",
      "Location": "Winreward"
    },
    {
      "ItemName": "",
      "Price": "",
      "Tier": "I",
      "GearScore": "54",
      "Availability": "4 7",
      "Location": "Winreward"
    },
    {
      "ItemName": "1 e Mata",
      "Price": "",
      "Tier": "",
      "GearScore": "",
      "Availability": "",
      "Location": "Winreward"
    },
    {
      "ItemName": "1 i Mate",
      "Price": "14",
      "Tier": "",
      "GearScore": "7",
      "Availability": "57",
      "Location": "Windeward"
    },
    {
      "ItemName": "Eecanna",
      "Price": "",
      "Tier": "V",
      "GearScore": "7",
      "Availability": "41",
      "Location": "Euarfall"
    },
    {
      "ItemName": "Eacanna",
      "Price": "11",
      "Tier": "V",
      "GearScore": "7",
      "Availability": "119",
      "Location": "Waeavara Fan"
    },
    {
      "ItemName": "Eacanna",
      "Price": "",
      "Tier": "V",
      "GearScore": "2",
      "Availability": "707",
      "Location": "Euarfall"
    },
    {
      "ItemName": "Eecanna",
      "Price": "",
      "Tier": "V",
      "GearScore": "7",
      "Availability": "147",
      "Location": "Windeward"
    },
    {
      "ItemName": "",
      "Price": "",
      "Tier": "",
      "GearScore": "7",
      "Availability": "2 1",
      "Location": ""
    },
    {
      "ItemName": "",
      "Price": "",
      "Tier": "",
      "GearScore": "",
      "Availability": "01",
      "Location": ""
    },
    {
      "ItemName": "",
      "Price": "",
      "Tier": "",
      "GearScore": "",
      "Availability": "027",
      "Location": ""
    },
    {
      "ItemName": "",
      "Price": "",
      "Tier": "",
      "GearScore": "",
      "Availability": "121",
      "Location": ""
    },
    {
      "ItemName": "",
      "Price": "",
      "Tier": "",
      "GearScore": "7",
      "Availability": "1",
      "Location": ""
    },
    {
      "ItemName": "",
      "Price": "",
      "Tier": "",
      "GearScore": "7",
      "Availability": "1",
      "Location": ""
    },
    {
      "ItemName": "",
      "Price": "",
      "Tier": "",
      "GearScore": "7",
      "Availability": "107",
      "Location": ""
    },
    {
      "ItemName": "",
      "Price": "",
      "Tier": "",
      "GearScore": "7",
      "Availability": "1 17",
      "Location": ""
    },
    {
      "ItemName": "",
      "Price": "",
      "Tier": "",
      "GearScore": "7",
      "Availability": "114",
      "Location": ""
    },
    {
      "ItemName": "Life Essence",
      "Price": "600",
      "Tier": "IV",
      "GearScore": "7",
      "Availability": "8",
      "Location": "Brightwood"
    },
    {
      "ItemName": "Life Wisp",
      "Price": "700",
      "Tier": "III",
      "GearScore": "2",
      "Availability": "28",
      "Location": "Everfall"
    },
    {
      "ItemName": "Life Wisp",
      "Price": "800",
      "Tier": "III",
      "GearScore": "3",
      "Availability": "15",
      "Location": "Cutlass Keys"
    },
    {
      "ItemName": "Life Wisp",
      "Price": "1000",
      "Tier": "III",
      "GearScore": "",
      "Availability": "44",
      "Location": "Everfall"
    },
    {
      "ItemName": "Life Wisp",
      "Price": "1500",
      "Tier": "III",
      "GearScore": "7",
      "Availability": "64",
      "Location": "Restless Shore"
    },
    {
      "ItemName": "Life Wisp",
      "Price": "1649",
      "Tier": "III",
      "GearScore": "7",
      "Availability": "27",
      "Location": "Everfall"
    },
    {
      "ItemName": "Life Quintessence",
      "Price": "1899",
      "Tier": "V",
      "GearScore": "7",
      "Availability": "27",
      "Location": "Restless Shore"
    },
    {
      "ItemName": "Life Quintessence",
      "Price": "1900",
      "Tier": "V",
      "GearScore": "7",
      "Availability": "168",
      "Location": "Everfall"
    },
    {
      "ItemName": "Life Quintessence",
      "Price": "2500",
      "Tier": "V",
      "GearScore": "7",
      "Availability": "469",
      "Location": "Evertall"
    },
    {
      "ItemName": "Death Mote",
      "Price": "110",
      "Tier": "II",
      "GearScore": "7",
      "Availability": "194",
      "Location": "Weaver's Fen"
    },
    {
      "ItemName": "Death Mote",
      "Price": "130",
      "Tier": "",
      "GearScore": "",
      "Availability": "395",
      "Location": "Weaver's Fen"
    },
    {
      "ItemName": "Death Mote",
      "Price": "130",
      "Tier": "II",
      "GearScore": "",
      "Availability": "96",
      "Location": "Windsward"
    },
    {
      "ItemName": "Death Mote",
      "Price": "130",
      "Tier": "II",
      "GearScore": "",
      "Availability": "28",
      "Location": "Evertall"
    },
    {
      "ItemName": "Death Mate",
      "Price": "148",
      "Tier": "II",
      "GearScore": "3",
      "Availability": "202",
      "Location": "Windsward"
    },
    {
      "ItemName": "Death Mote",
      "Price": "148",
      "Tier": "II",
      "GearScore": "7",
      "Availability": "38",
      "Location": "Everfall"
    },
    {
      "ItemName": "Death Mote",
      "Price": "148",
      "Tier": "II",
      "GearScore": "5",
      "Availability": "132",
      "Location": "Everfall"
    },
    {
      "ItemName": "Death Mote",
      "Price": "149",
      "Tier": "II",
      "GearScore": "7",
      "Availability": "29",
      "Location": "Mourningdale"
    },
    {
      "ItemName": "Death Mote",
      "Price": "150",
      "Tier": "II",
      "GearScore": "5",
      "Availability": "268",
      "Location": "Windsward"
    },
    {
      "ItemName": "Death Mote",
      "Price": "",
      "Tier": "II",
      "GearScore": "7",
      "Availability": "29",
      "Location": "Mourningdale"
    },
    {
      "ItemName": "Death Mate",
      "Price": "150",
      "Tier": "II",
      "GearScore": "7",
      "Availability": "268",
      "Location": "Windsward"
    },
    {
      "ItemName": "Death Mote",
      "Price": "150",
      "Tier": "II",
      "GearScore": "1",
      "Availability": "76",
      "Location": "Everfall"
    },
    {
      "ItemName": "Death Mote",
      "Price": "160",
      "Tier": "II",
      "GearScore": "7",
      "Availability": "231",
      "Location": "Everfall"
    },
    {
      "ItemName": "Death Mote",
      "Price": "160",
      "Tier": "II",
      "GearScore": "7",
      "Availability": "100",
      "Location": "Windsward"
    },
    {
      "ItemName": "Death Mote",
      "Price": "168",
      "Tier": "II",
      "GearScore": "7",
      "Availability": "49",
      "Location": "Restless Shore"
    },
    {
      "ItemName": "Death Mote",
      "Price": "180",
      "Tier": "II",
      "GearScore": "7",
      "Availability": "60",
      "Location": "Windsward"
    },
    {
      "ItemName": "Death Mote",
      "Price": "180",
      "Tier": "II",
      "GearScore": "7",
      "Availability": "300",
      "Location": "Windsward"
    },
    {
      "ItemName": "Death Mote",
      "Price": "230",
      "Tier": "II",
      "GearScore": "7",
      "Availability": "15",
      "Location": "Weaver's Fen"
    },
    {
      "ItemName": "",
      "Price": "",
      "Tier": "",
      "GearScore": "4",
      "Availability": "14",
      "Location": ""
    },
    {
      "ItemName": "",
      "Price": "",
      "Tier": "",
      "GearScore": "",
      "Availability": "1 1",
      "Location": ""
    },
    {
      "ItemName": "",
      "Price": "",
      "Tier": "",
      "GearScore": "",
      "Availability": "19",
      "Location": ""
    },
    {
      "ItemName": "",
      "Price": "",
      "Tier": "",
      "GearScore": "",
      "Availability": "01",
      "Location": ""
    },
    {
      "ItemName": "",
      "Price": "",
      "Tier": "",
      "GearScore": "",
      "Availability": "11",
      "Location": ""
    },
    {
      "ItemName": "",
      "Price": "",
      "Tier": "",
      "GearScore": "7",
      "Availability": "4 0",
      "Location": ""
    },
    {
      "ItemName": "",
      "Price": "",
      "Tier": "IV",
      "GearScore": "",
      "Availability": "1",
      "Location": ""
    },
    {
      "ItemName": "",
      "Price": "",
      "Tier": "",
      "GearScore": "7  17 77",
      "Availability": "170",
      "Location": ""
    },
    {
      "ItemName": "",
      "Price": "",
      "Tier": "",
      "GearScore": "7",
      "Availability": "1 1",
      "Location": ""
    },
    {
      "ItemName": "Soul Mote",
      "Price": "149",
      "Tier": "II",
      "GearScore": "7",
      "Availability": "119",
      "Location": "Everfall"
    },
    {
      "ItemName": "Soul Mote",
      "Price": "149",
      "Tier": "II",
      "GearScore": "7",
      "Availability": "329",
      "Location": "Restless Shore"
    },
    {
      "ItemName": "Soul Mote",
      "Price": "150",
      "Tier": "II",
      "GearScore": "1",
      "Availability": "12",
      "Location": "Monarch's Bluffs"
    },
    {
      "ItemName": "Soul Mote",
      "Price": "155",
      "Tier": "II",
      "GearScore": "",
      "Availability": "3",
      "Location": "Everfall"
    },
    {
      "ItemName": "Soul Mote",
      "Price": "155",
      "Tier": "II",
      "GearScore": "7",
      "Availability": "118",
      "Location": "Cutlass Keys"
    },
    {
      "ItemName": "Soul Mote",
      "Price": "197",
      "Tier": "II",
      "GearScore": "7",
      "Availability": "101",
      "Location": "Windsward"
    },
    {
      "ItemName": "Soul Mote",
      "Price": "200",
      "Tier": "II",
      "GearScore": "5",
      "Availability": "106",
      "Location": "Windsward"
    },
    {
      "ItemName": "Soul Mote",
      "Price": "235",
      "Tier": "II",
      "GearScore": "7",
      "Availability": "98",
      "Location": "Cutlass Keys"
    },
    {
      "ItemName": "Soul Mote",
      "Price": "299",
      "Tier": "II",
      "GearScore": "7",
      "Availability": "316",
      "Location": "Evertall"
    },
    {
      "ItemName": "",
      "Price": "",
      "Tier": "",
      "GearScore": "7",
      "Availability": "4",
      "Location": ""
    },
    {
      "ItemName": "",
      "Price": "",
      "Tier": "",
      "GearScore": "7",
      "Availability": "2 1 1",
      "Location": ""
    },
    {
      "ItemName": "",
      "Price": "",
      "Tier": "",
      "GearScore": "",
      "Availability": "01 1",
      "Location": "Dttt A"
    },
    {
      "ItemName": "",
      "Price": "",
      "Tier": "",
      "GearScore": "",
      "Availability": "1",
      "Location": ""
    },
    {
      "ItemName": "",
      "Price": "",
      "Tier": "",
      "GearScore": "7",
      "Availability": "1 1",
      "Location": "e"
    },
    {
      "ItemName": "",
      "Price": "",
      "Tier": "",
      "GearScore": "7",
      "Availability": "0",
      "Location": ""
    },
    {
      "ItemName": "",
      "Price": "",
      "Tier": "",
      "GearScore": "7",
      "Availability": "1",
      "Location": ""
    },
    {
      "ItemName": "",
      "Price": "",
      "Tier": "",
      "GearScore": "2",
      "Availability": "4",
      "Location": "e T"
    },
    {
      "ItemName": "",
      "Price": "",
      "Tier": "",
      "GearScore": "7",
      "Availability": "",
      "Location": ""
    },
    {
      "ItemName": "Fire Mote",
      "Price": "100",
      "Tier": "II",
      "GearScore": "",
      "Availability": "133",
      "Location": "Windsward"
    },
    {
      "ItemName": "Fire Mote",
      "Price": "100",
      "Tier": "II",
      "GearScore": "",
      "Availability": "1089",
      "Location": "Windsward"
    },
    {
      "ItemName": "Fire Mote",
      "Price": "110",
      "Tier": "II",
      "GearScore": "",
      "Availability": "143",
      "Location": "Windsward"
    },
    {
      "ItemName": "Fire Mote",
      "Price": "110",
      "Tier": "II",
      "GearScore": "7",
      "Availability": "24",
      "Location": "Windsward"
    },
    {
      "ItemName": "Fire Mote",
      "Price": "115",
      "Tier": "II",
      "GearScore": "7",
      "Availability": "50",
      "Location": "Windsward"
    },
    {
      "ItemName": "Fire Mote",
      "Price": "132",
      "Tier": "II",
      "GearScore": "7",
      "Availability": "611",
      "Location": "First Light"
    },
    {
      "ItemName": "Fire Mote",
      "Price": "132",
      "Tier": "II",
      "GearScore": "5",
      "Availability": "15",
      "Location": "Evertall"
    },
    {
      "ItemName": "Fire Mote",
      "Price": "13",
      "Tier": "II",
      "GearScore": "7",
      "Availability": "62",
      "Location": "Brightwood"
    },
    {
      "ItemName": "Fire Mote",
      "Price": "134",
      "Tier": "II",
      "GearScore": "7",
      "Availability": "144",
      "Location": "Evertall"
    },
    {
      "ItemName": "Fire Mote",
      "Price": "14",
      "Tier": "",
      "GearScore": "7",
      "Availability": "611",
      "Location": "First Light"
    },
    {
      "ItemName": "Fire Mote",
      "Price": "1",
      "Tier": "",
      "GearScore": "",
      "Availability": "15",
      "Location": "Evertall"
    },
    {
      "ItemName": "Fire Mote",
      "Price": "135",
      "Tier": "",
      "GearScore": "",
      "Availability": "2",
      "Location": "Brightwood"
    },
    {
      "ItemName": "Fire Mote",
      "Price": "19",
      "Tier": "",
      "GearScore": "",
      "Availability": "144",
      "Location": "Evertall"
    },
    {
      "ItemName": "Fire Mote",
      "Price": "13",
      "Tier": "",
      "GearScore": "7",
      "Availability": "1",
      "Location": "Evertall"
    },
    {
      "ItemName": "Fire Mote",
      "Price": "1",
      "Tier": "",
      "GearScore": "7",
      "Availability": "136",
      "Location": "First Light"
    },
    {
      "ItemName": "Fire Mote",
      "Price": "1457",
      "Tier": "",
      "GearScore": "7",
      "Availability": "6",
      "Location": "Restiess Shore."
    },
    {
      "ItemName": "Fire Mote",
      "Price": "7130",
      "Tier": "",
      "GearScore": "7",
      "Availability": "7",
      "Location": "Evertall"
    },
    {
      "ItemName": "Fire Mote",
      "Price": "13",
      "Tier": "",
      "GearScore": "7",
      "Availability": "0",
      "Location": "Windsward"
    },
    {
      "ItemName": "",
      "Price": "",
      "Tier": "",
      "GearScore": "3",
      "Availability": "401",
      "Location": "e"
    },
    {
      "ItemName": "",
      "Price": "",
      "Tier": "",
      "GearScore": "7",
      "Availability": "1 1 1",
      "Location": ""
    },
    {
      "ItemName": "",
      "Price": "",
      "Tier": "",
      "GearScore": "",
      "Availability": "",
      "Location": ""
    },
    {
      "ItemName": "",
      "Price": "",
      "Tier": "",
      "GearScore": "",
      "Availability": "101",
      "Location": ""
    },
    {
      "ItemName": "",
      "Price": "",
      "Tier": "",
      "GearScore": "",
      "Availability": "04",
      "Location": ""
    },
    {
      "ItemName": "",
      "Price": "",
      "Tier": "",
      "GearScore": "7",
      "Availability": "047",
      "Location": ""
    },
    {
      "ItemName": "",
      "Price": "",
      "Tier": "",
      "GearScore": "7",
      "Availability": "4 1",
      "Location": ""
    },
    {
      "ItemName": "",
      "Price": "",
      "Tier": "",
      "GearScore": "7",
      "Availability": "17",
      "Location": ""
    },
    {
      "ItemName": "",
      "Price": "",
      "Tier": "",
      "GearScore": "7",
      "Availability": "4 717",
      "Location": ""
    },
    {
      "ItemName": "Earth Mote",
      "Price": "108",
      "Tier": "II",
      "GearScore": "",
      "Availability": "50",
      "Location": "Windsward"
    },
    {
      "ItemName": "Earth Mote",
      "Price": "108",
      "Tier": "II",
      "GearScore": "",
      "Availability": "8",
      "Location": "Windsward"
    },
    {
      "ItemName": "Earth Mote",
      "Price": "109",
      "Tier": "II",
      "GearScore": "",
      "Availability": "51",
      "Location": "Weaver's Fen"
    },
    {
      "ItemName": "Earth Mote",
      "Price": "120",
      "Tier": "II",
      "GearScore": "",
      "Availability": "87",
      "Location": "Weaver's Fen"
    },
    {
      "ItemName": "Earth Mote",
      "Price": "140",
      "Tier": "II",
      "GearScore": "7",
      "Availability": "108",
      "Location": "Reekwater"
    },
    {
      "ItemName": "Earth Mote",
      "Price": "144",
      "Tier": "II",
      "GearScore": "7",
      "Availability": "107",
      "Location": "Windsward"
    },
    {
      "ItemName": "Earth Mote",
      "Price": "149",
      "Tier": "II",
      "GearScore": "7",
      "Availability": "217",
      "Location": "Everfall"
    },
    {
      "ItemName": "Earth Mote",
      "Price": "150",
      "Tier": "II",
      "GearScore": "2",
      "Availability": "250",
      "Location": "Windsward"
    },
    {
      "ItemName": "Earth Mote",
      "Price": "168",
      "Tier": "II",
      "GearScore": "7",
      "Availability": "59",
      "Location": "Evonscale Reach"
    },
    {
      "ItemName": "Earth Mote",
      "Price": "168",
      "Tier": "II",
      "GearScore": "7",
      "Availability": "59",
      "Location": "Ebonscale Reach"
    },
    {
      "ItemName": "Earth Mote",
      "Price": "169",
      "Tier": "",
      "GearScore": "7",
      "Availability": "497",
      "Location": "Brightwood"
    },
    {
      "ItemName": "Earth Mote",
      "Price": "169",
      "Tier": "II",
      "GearScore": "",
      "Availability": "285",
      "Location": "Cutlass Keys"
    },
    {
      "ItemName": "Earth Mote",
      "Price": "170",
      "Tier": "II",
      "GearScore": "7",
      "Availability": "601",
      "Location": "Everfall"
    },
    {
      "ItemName": "Earth Mote",
      "Price": "198",
      "Tier": "II",
      "GearScore": "7",
      "Availability": "100",
      "Location": "Everfall"
    },
    {
      "ItemName": "Earth Mote",
      "Price": "",
      "Tier": "II",
      "GearScore": "7",
      "Availability": "119",
      "Location": "First Light"
    },
    {
      "ItemName": "Earth Mote",
      "Price": "200",
      "Tier": "II",
      "GearScore": "2",
      "Availability": "60",
      "Location": "Windsward"
    },
    {
      "ItemName": "Earth Wisp",
      "Price": "5000",
      "Tier": "III",
      "GearScore": "",
      "Availability": "28",
      "Location": "Cutlass Keys"
    },
    {
      "ItemName": "Earth Quintessence",
      "Price": "6200",
      "Tier": "V",
      "GearScore": "2",
      "Availability": "19",
      "Location": "Everfall"
    },
    {
      "ItemName": "",
      "Price": "",
      "Tier": "",
      "GearScore": "7",
      "Availability": "1101",
      "Location": "Syt bt"
    },
    {
      "ItemName": "",
      "Price": "",
      "Tier": "",
      "GearScore": "",
      "Availability": "114",
      "Location": ""
    },
    {
      "ItemName": "",
      "Price": "",
      "Tier": "",
      "GearScore": "",
      "Availability": "10",
      "Location": ""
    },
    {
      "ItemName": "",
      "Price": "",
      "Tier": "",
      "GearScore": "",
      "Availability": "1",
      "Location": "ST"
    },
    {
      "ItemName": "",
      "Price": "14511",
      "Tier": "",
      "GearScore": "7",
      "Availability": "00",
      "Location": ""
    },
    {
      "ItemName": "",
      "Price": "",
      "Tier": "",
      "GearScore": "7",
      "Availability": "10",
      "Location": "Dttt A"
    },
    {
      "ItemName": "",
      "Price": "",
      "Tier": "",
      "GearScore": "7",
      "Availability": "1",
      "Location": ""
    },
    {
      "ItemName": "",
      "Price": "",
      "Tier": "",
      "GearScore": "7",
      "Availability": "1",
      "Location": ""
    },
    {
      "ItemName": "",
      "Price": "",
      "Tier": "",
      "GearScore": "7",
      "Availability": "1",
      "Location": ""
    },
    {
      "ItemName": "Air Mote",
      "Price": "160",
      "Tier": "II",
      "GearScore": "7",
      "Availability": "12",
      "Location": "Everfall"
    },
    {
      "ItemName": "Air Mote",
      "Price": "160",
      "Tier": "II",
      "GearScore": "7",
      "Availability": "421",
      "Location": "Monarch's Bluffs"
    },
    {
      "ItemName": "Air Mote",
      "Price": "168",
      "Tier": "II",
      "GearScore": "1",
      "Availability": "130",
      "Location": "Everfall"
    },
    {
      "ItemName": "Air Mote",
      "Price": "169",
      "Tier": "II",
      "GearScore": "",
      "Availability": "38",
      "Location": "Reekwater"
    },
    {
      "ItemName": "Air Mote",
      "Price": "184",
      "Tier": "II",
      "GearScore": "7",
      "Availability": "26",
      "Location": "Mourningdale"
    },
    {
      "ItemName": "Air Mote",
      "Price": "185",
      "Tier": "II",
      "GearScore": "7",
      "Availability": "1",
      "Location": "Everfall"
    },
    {
      "ItemName": "Air Mote",
      "Price": "190",
      "Tier": "II",
      "GearScore": "7",
      "Availability": "258",
      "Location": "Everfall"
    },
    {
      "ItemName": "Air Mote",
      "Price": "198",
      "Tier": "II",
      "GearScore": "7",
      "Availability": "196",
      "Location": "Everfall"
    },
    {
      "ItemName": "Air Mote",
      "Price": "200",
      "Tier": "II",
      "GearScore": "7",
      "Availability": "364",
      "Location": "Evertall"
    },
    {
      "ItemName": "Air Mote",
      "Price": "185",
      "Tier": "II",
      "GearScore": "",
      "Availability": "1",
      "Location": "Everfall"
    },
    {
      "ItemName": "Air Mote",
      "Price": "190",
      "Tier": "II",
      "GearScore": "",
      "Availability": "258",
      "Location": "Everfall"
    },
    {
      "ItemName": "Air Mote",
      "Price": "198",
      "Tier": "II",
      "GearScore": "",
      "Availability": "196",
      "Location": "Evertall"
    },
    {
      "ItemName": "Air Mote",
      "Price": "200",
      "Tier": "II",
      "GearScore": "7",
      "Availability": "364",
      "Location": "Everfall"
    },
    {
      "ItemName": "Air Mote",
      "Price": "22",
      "Tier": "II",
      "GearScore": "7",
      "Availability": "1000",
      "Location": "Monarch's Bluffs"
    },
    {
      "ItemName": "Air Mote",
      "Price": "250",
      "Tier": "II",
      "GearScore": "7",
      "Availability": "404",
      "Location": "Cutlass Keys"
    },
    {
      "ItemName": "Air Wisp",
      "Price": "5000",
      "Tier": "III",
      "GearScore": "7",
      "Availability": "15",
      "Location": "Cutlass Keys"
    },
    {
      "ItemName": "Air Essence",
      "Price": "7000",
      "Tier": "IV",
      "GearScore": "",
      "Availability": "59",
      "Location": "Windsward"
    },
    {
      "ItemName": "Air Essence",
      "Price": "7000",
      "Tier": "IV",
      "GearScore": "7",
      "Availability": "108",
      "Location": "Everfall"
    },
    {
      "ItemName": "",
      "Price": "1451",
      "Tier": "",
      "GearScore": "7",
      "Availability": "11",
      "Location": "ke’"
    },
    {
      "ItemName": "",
      "Price": "",
      "Tier": "",
      "GearScore": "",
      "Availability": "1",
      "Location": "Dttt A"
    },
    {
      "ItemName": "",
      "Price": "",
      "Tier": "",
      "GearScore": "",
      "Availability": "1  0",
      "Location": ""
    },
    {
      "ItemName": "",
      "Price": "",
      "Tier": "",
      "GearScore": "",
      "Availability": "1 1",
      "Location": ""
    },
    {
      "ItemName": "",
      "Price": "",
      "Tier": "",
      "GearScore": "7",
      "Availability": "4",
      "Location": ""
    },
    {
      "ItemName": "",
      "Price": "",
      "Tier": "",
      "GearScore": "7",
      "Availability": "141",
      "Location": ""
    },
    {
      "ItemName": "",
      "Price": "",
      "Tier": "",
      "GearScore": "",
      "Availability": "1",
      "Location": ""
    },
    {
      "ItemName": "",
      "Price": "",
      "Tier": "",
      "GearScore": "7  5 7",
      "Availability": "11",
      "Location": ""
    },
    {
      "ItemName": "",
      "Price": "",
      "Tier": "",
      "GearScore": "7",
      "Availability": "",
      "Location": "e TR"
    },
    {
      "ItemName": "Earth Mote",
      "Price": "108",
      "Tier": "II",
      "GearScore": "",
      "Availability": "50",
      "Location": "Windsward"
    },
    {
      "ItemName": "Earth Mote",
      "Price": "108",
      "Tier": "II",
      "GearScore": "",
      "Availability": "8",
      "Location": "Windsward"
    },
    {
      "ItemName": "Earth Mote",
      "Price": "109",
      "Tier": "II",
      "GearScore": "",
      "Availability": "51",
      "Location": "Weaver's Fen"
    },
    {
      "ItemName": "Earth Mote",
      "Price": "120",
      "Tier": "II",
      "GearScore": "7",
      "Availability": "87",
      "Location": "Weaver's Fen"
    },
    {
      "ItemName": "Earth Mote",
      "Price": "140",
      "Tier": "II",
      "GearScore": "7",
      "Availability": "108",
      "Location": "Reekwater"
    },
    {
      "ItemName": "Earth Mote",
      "Price": "144",
      "Tier": "II",
      "GearScore": "7",
      "Availability": "107",
      "Location": "Windsward"
    },
    {
      "ItemName": "Earth Mote",
      "Price": "149",
      "Tier": "II",
      "GearScore": "7",
      "Availability": "217",
      "Location": "Everfall"
    },
    {
      "ItemName": "Earth Mote",
      "Price": "150",
      "Tier": "II",
      "GearScore": "7",
      "Availability": "250",
      "Location": "Windsward"
    },
    {
      "ItemName": "Earth Mote",
      "Price": "168",
      "Tier": "II",
      "GearScore": "7",
      "Availability": "59",
      "Location": "Evonscale Reach"
    },
    {
      "ItemName": "Air Mote",
      "Price": "160",
      "Tier": "II",
      "GearScore": "7",
      "Availability": "12",
      "Location": "Everfall"
    },
    {
      "ItemName": "Air Mote",
      "Price": "160",
      "Tier": "",
      "GearScore": "4",
      "Availability": "421",
      "Location": "Monarch's Bluffs"
    },
    {
      "ItemName": "Air Mote",
      "Price": "168",
      "Tier": "II",
      "GearScore": "1",
      "Availability": "130",
      "Location": "Everfall"
    },
    {
      "ItemName": "Air Mote",
      "Price": "169",
      "Tier": "II",
      "GearScore": "",
      "Availability": "38",
      "Location": "Reekwater"
    },
    {
      "ItemName": "Air Mote",
      "Price": "184",
      "Tier": "II",
      "GearScore": "7",
      "Availability": "26",
      "Location": "Mourningdale"
    },
    {
      "ItemName": "Air Mote",
      "Price": "185",
      "Tier": "II",
      "GearScore": "5",
      "Availability": "1",
      "Location": "Everfall"
    },
    {
      "ItemName": "Air Mote",
      "Price": "190",
      "Tier": "II",
      "GearScore": "5",
      "Availability": "258",
      "Location": "Everfall"
    },
    {
      "ItemName": "Air Mote",
      "Price": "198",
      "Tier": "II",
      "GearScore": "7",
      "Availability": "196",
      "Location": "Everfall"
    },
    {
      "ItemName": "Air Mote",
      "Price": "200",
      "Tier": "II",
      "GearScore": "7",
      "Availability": "364",
      "Location": "Evertall"
    },
    {
      "ItemName": "Air Mote",
      "Price": "190",
      "Tier": "II",
      "GearScore": "7",
      "Availability": "258",
      "Location": "Everfall"
    },
    {
      "ItemName": "Air Mote",
      "Price": "198",
      "Tier": "II",
      "GearScore": "7",
      "Availability": "196",
      "Location": "Evertall"
    },
    {
      "ItemName": "Air Mote",
      "Price": "200",
      "Tier": "II",
      "GearScore": "",
      "Availability": "264",
      "Location": "Everfall"
    },
    {
      "ItemName": "Air Mote",
      "Price": "224",
      "Tier": "II",
      "GearScore": "",
      "Availability": "1000",
      "Location": "Monarch's Bluffs"
    },
    {
      "ItemName": "Air Mote",
      "Price": "250",
      "Tier": "II",
      "GearScore": "3",
      "Availability": "404",
      "Location": "Cutlass Kevs"
    },
    {
      "ItemName": "Air Wisp",
      "Price": "5000",
      "Tier": "III",
      "GearScore": "7",
      "Availability": "115",
      "Location": "Cutlass Kevs"
    },
    {
      "ItemName": "Air Essence",
      "Price": "7000",
      "Tier": "IV",
      "GearScore": "7",
      "Availability": "59",
      "Location": "Windsward"
    },
    {
      "ItemName": "Air Essence",
      "Price": "7000",
      "Tier": "IV",
      "GearScore": "7",
      "Availability": "108",
      "Location": "Everfall"
    },
    {
      "ItemName": "Air Quintessence",
      "Price": "9200",
      "Tier": "V",
      "GearScore": "",
      "Availability": "1",
      "Location": "Monarch's Bluffs"
    },
    {
      "ItemName": "",
      "Price": "1451",
      "Tier": "",
      "GearScore": "2",
      "Availability": "11",
      "Location": "i e"
    },
    {
      "ItemName": "",
      "Price": "",
      "Tier": "IIV",
      "GearScore": "",
      "Availability": "",
      "Location": "Dt A"
    },
    {
      "ItemName": "",
      "Price": "",
      "Tier": "",
      "GearScore": "",
      "Availability": "1  0",
      "Location": ""
    },
    {
      "ItemName": "",
      "Price": "",
      "Tier": "",
      "GearScore": "",
      "Availability": "1 1",
      "Location": ""
    },
    {
      "ItemName": "",
      "Price": "",
      "Tier": "",
      "GearScore": "7",
      "Availability": "4",
      "Location": ""
    },
    {
      "ItemName": "",
      "Price": "",
      "Tier": "",
      "GearScore": "7",
      "Availability": "141",
      "Location": ""
    },
    {
      "ItemName": "",
      "Price": "",
      "Tier": "",
      "GearScore": "7",
      "Availability": "1",
      "Location": ""
    },
    {
      "ItemName": "",
      "Price": "",
      "Tier": "",
      "GearScore": "7",
      "Availability": "11",
      "Location": ""
    },
    {
      "ItemName": "",
      "Price": "",
      "Tier": "",
      "GearScore": "7",
      "Availability": "",
      "Location": "e TR"
    },
    {
      "ItemName": "Air Quintessence",
      "Price": "10900",
      "Tier": "V",
      "GearScore": "7",
      "Availability": "2",
      "Location": "Evonscale Reach"
    },
    {
      "ItemName": "Air Quintessence",
      "Price": "10900",
      "Tier": "V",
      "GearScore": "",
      "Availability": "20",
      "Location": "Everfall"
    },
    {
      "ItemName": "",
      "Price": "",
      "Tier": "",
      "GearScore": "",
      "Availability": "",
      "Location": ""
    },
    {
      "ItemName": "",
      "Price": "",
      "Tier": "",
      "GearScore": "2",
      "Availability": "",
      "Location": ""
    },
    {
      "ItemName": "",
      "Price": "",
      "Tier": "",
      "GearScore": "",
      "Availability": "",
      "Location": ""
    },
    {
      "ItemName": "",
      "Price": "",
      "Tier": "",
      "GearScore": "9",
      "Availability": "",
      "Location": ""
    },
    {
      "ItemName": "",
      "Price": "",
      "Tier": "",
      "GearScore": "",
      "Availability": "",
      "Location": ""
    },
    {
      "ItemName": "",
      "Price": "",
      "Tier": "",
      "GearScore": "",
      "Availability": "",
      "Location": ""
    },
    {
      "ItemName": "",
      "Price": "",
      "Tier": "",
      "GearScore": "5",
      "Availability": "",
      "Location": ""
    },
    {
      "ItemName": "Air Quintessence",
      "Price": "9200",
      "Tier": "",
      "GearScore": "",
      "Availability": "1",
      "Location": "Monarch's Bluffs"
    },
    {
      "ItemName": "Air Quintessence",
      "Price": "9200",
      "Tier": "V",
      "GearScore": "7",
      "Availability": "4",
      "Location": "Ebonscale Reach"
    },
    {
      "ItemName": "Air Quintessence",
      "Price": "9900",
      "Tier": "V",
      "GearScore": "",
      "Availability": "20",
      "Location": "Everfall"
    },
    {
      "ItemName": "Air Quintessence",
      "Price": "10800",
      "Tier": "V",
      "GearScore": "",
      "Availability": "22",
      "Location": "Evertall"
    },
    {
      "ItemName": "Air Quintessence",
      "Price": "10900",
      "Tier": "V",
      "GearScore": "7",
      "Availability": "2",
      "Location": "Ebonscale Reach"
    },
    {
      "ItemName": "Air Quintessence",
      "Price": "10900",
      "Tier": "V",
      "GearScore": "7",
      "Availability": "20",
      "Location": "Everfall"
    },
    {
      "ItemName": "",
      "Price": "",
      "Tier": "",
      "GearScore": "",
      "Availability": "",
      "Location": ""
    },
    {
      "ItemName": "",
      "Price": "",
      "Tier": "",
      "GearScore": "",
      "Availability": "1",
      "Location": ""
    },
    {
      "ItemName": "",
      "Price": "",
      "Tier": "",
      "GearScore": "",
      "Availability": "5",
      "Location": ""
    },
    {
      "ItemName": "Water Mote",
      "Price": "110",
      "Tier": "",
      "GearScore": "",
      "Availability": "164",
      "Location": "Weaver's Fen"
    },
    {
      "ItemName": "Water Mote",
      "Price": "110",
      "Tier": "II",
      "GearScore": "",
      "Availability": "89",
      "Location": "Windsward"
    },
    {
      "ItemName": "Water Mote",
      "Price": "14",
      "Tier": "II",
      "GearScore": "",
      "Availability": "88",
      "Location": "Everfall"
    },
    {
      "ItemName": "Water Mote",
      "Price": "14",
      "Tier": "II",
      "GearScore": "",
      "Availability": "306",
      "Location": "Reekwater"
    },
    {
      "ItemName": "Water Mate",
      "Price": "115",
      "Tier": "II",
      "GearScore": "3",
      "Availability": "50",
      "Location": "Windsward"
    },
    {
      "ItemName": "Water Mote",
      "Price": "115",
      "Tier": "II",
      "GearScore": "7",
      "Availability": "75",
      "Location": "Windsward"
    },
    {
      "ItemName": "Water Mote",
      "Price": "115",
      "Tier": "II",
      "GearScore": "7",
      "Availability": "30",
      "Location": "Everfall"
    },
    {
      "ItemName": "Water Mote",
      "Price": "118",
      "Tier": "II",
      "GearScore": "7",
      "Availability": "40",
      "Location": "Mourningdale"
    },
    {
      "ItemName": "Water Mote",
      "Price": "118",
      "Tier": "II",
      "GearScore": "7",
      "Availability": "43",
      "Location": "Evertall"
    },
    {
      "ItemName": "Water Mote",
      "Price": "115",
      "Tier": "II",
      "GearScore": "",
      "Availability": "75",
      "Location": "Windsward"
    },
    {
      "ItemName": "Water Mote",
      "Price": "115",
      "Tier": "II",
      "GearScore": "7",
      "Availability": "30",
      "Location": "Everfall"
    },
    {
      "ItemName": "Water Mote",
      "Price": "118",
      "Tier": "II",
      "GearScore": "1",
      "Availability": "40",
      "Location": "Mourningdale"
    },
    {
      "ItemName": "Water Mote",
      "Price": "118",
      "Tier": "II",
      "GearScore": "7",
      "Availability": "43",
      "Location": "Evertall"
    },
    {
      "ItemName": "Water Mote",
      "Price": "119",
      "Tier": "II",
      "GearScore": "7",
      "Availability": "61",
      "Location": "Everfall"
    },
    {
      "ItemName": "Water Mate",
      "Price": "120",
      "Tier": "II",
      "GearScore": "7",
      "Availability": "29",
      "Location": "Everfall"
    },
    {
      "ItemName": "Water Mote",
      "Price": "122",
      "Tier": "II",
      "GearScore": "7",
      "Availability": "300",
      "Location": "Weaver's Fen"
    },
    {
      "ItemName": "Water Mote",
      "Price": "122",
      "Tier": "II",
      "GearScore": "",
      "Availability": "200",
      "Location": "Windsward"
    },
    {
      "ItemName": "Water Mote",
      "Price": "123",
      "Tier": "II",
      "GearScore": "3",
      "Availability": "291",
      "Location": "Windsward"
    },
    {
      "ItemName": "",
      "Price": "",
      "Tier": "",
      "GearScore": "2",
      "Availability": "5 1  1",
      "Location": ""
    },
    {
      "ItemName": "",
      "Price": "",
      "Tier": "",
      "GearScore": "",
      "Availability": "1",
      "Location": ""
    },
    {
      "ItemName": "",
      "Price": "",
      "Tier": "",
      "GearScore": "",
      "Availability": "001",
      "Location": ""
    },
    {
      "ItemName": "",
      "Price": "",
      "Tier": "",
      "GearScore": "",
      "Availability": "12",
      "Location": ""
    },
    {
      "ItemName": "",
      "Price": "",
      "Tier": "",
      "GearScore": "7",
      "Availability": "11   3",
      "Location": ""
    },
    {
      "ItemName": "",
      "Price": "",
      "Tier": "",
      "GearScore": "7",
      "Availability": "0 1",
      "Location": ""
    },
    {
      "ItemName": "",
      "Price": "",
      "Tier": "",
      "GearScore": "7",
      "Availability": "2",
      "Location": ""
    },
    {
      "ItemName": "",
      "Price": "",
      "Tier": "",
      "GearScore": "7",
      "Availability": "00",
      "Location": ""
    },
    {
      "ItemName": "",
      "Price": "",
      "Tier": "",
      "GearScore": "7",
      "Availability": "1 1 1",
      "Location": ""
    },
    {
      "ItemName": "Water Essence",
      "Price": "3500",
      "Tier": "IV",
      "GearScore": "7",
      "Availability": "20",
      "Location": "Everfall"
    },
    {
      "ItemName": "Water Quintessence",
      "Price": "4800",
      "Tier": "V",
      "GearScore": "",
      "Availability": "6",
      "Location": "Everfall"
    },
    {
      "ItemName": "Water Quintessence",
      "Price": "4900",
      "Tier": "V",
      "GearScore": "",
      "Availability": "49",
      "Location": "Everfall"
    },
    {
      "ItemName": "Water Quintessence",
      "Price": "5000",
      "Tier": "V",
      "GearScore": "",
      "Availability": "4",
      "Location": "Evertall"
    },
    {
      "ItemName": "Water Quintessence",
      "Price": "5200",
      "Tier": "V",
      "GearScore": "7",
      "Availability": "21",
      "Location": "Everfall"
    },
    {
      "ItemName": "",
      "Price": "",
      "Tier": "",
      "GearScore": "9",
      "Availability": "",
      "Location": ""
    },
    {
      "ItemName": "",
      "Price": "",
      "Tier": "",
      "GearScore": "1 314",
      "Availability": "",
      "Location": ""
    },
    {
      "ItemName": "",
      "Price": "",
      "Tier": "",
      "GearScore": "141   7 5  1  2",
      "Availability": "",
      "Location": ""
    },
    {
      "ItemName": "",
      "Price": "",
      "Tier": "",
      "GearScore": "",
      "Availability": "3",
      "Location": ""
    }
  ],
  "InvalidPriceData": [
    {
      "ItemName": "",
      "Price": "",
      "Tier": "",
      "GearScore": "7",
      "Availability": "2 1",
      "Location": ""
    },
    {
      "ItemName": "",
      "Price": "",
      "Tier": "",
      "GearScore": "",
      "Availability": "01",
      "Location": ""
    },
    {
      "ItemName": "",
      "Price": "",
      "Tier": "",
      "GearScore": "",
      "Availability": "027",
      "Location": ""
    },
    {
      "ItemName": "",
      "Price": "",
      "Tier": "",
      "GearScore": "",
      "Availability": "121",
      "Location": ""
    },
    {
      "ItemName": "",
      "Price": "",
      "Tier": "",
      "GearScore": "7",
      "Availability": "1",
      "Location": ""
    },
    {
      "ItemName": "",
      "Price": "",
      "Tier": "",
      "GearScore": "7",
      "Availability": "1",
      "Location": ""
    },
    {
      "ItemName": "",
      "Price": "",
      "Tier": "",
      "GearScore": "7",
      "Availability": "107",
      "Location": ""
    },
    {
      "ItemName": "",
      "Price": "",
      "Tier": "",
      "GearScore": "7",
      "Availability": "1 17",
      "Location": ""
    },
    {
      "ItemName": "",
      "Price": "",
      "Tier": "",
      "GearScore": "7",
      "Availability": "114",
      "Location": ""
    },
    {
      "ItemName": "Death Mote",
      "Price": "",
      "Tier": "II",
      "GearScore": "7",
      "Availability": "29",
      "Location": "Mourningdale"
    },
    {
      "ItemName": "",
      "Price": "",
      "Tier": "",
      "GearScore": "4",
      "Availability": "14",
      "Location": ""
    },
    {
      "ItemName": "",
      "Price": "",
      "Tier": "",
      "GearScore": "",
      "Availability": "1 1",
      "Location": ""
    },
    {
      "ItemName": "",
      "Price": "",
      "Tier": "",
      "GearScore": "",
      "Availability": "19",
      "Location": ""
    },
    {
      "ItemName": "",
      "Price": "",
      "Tier": "",
      "GearScore": "",
      "Availability": "01",
      "Location": ""
    },
    {
      "ItemName": "",
      "Price": "",
      "Tier": "",
      "GearScore": "",
      "Availability": "11",
      "Location": ""
    },
    {
      "ItemName": "",
      "Price": "",
      "Tier": "",
      "GearScore": "7",
      "Availability": "4 0",
      "Location": ""
    },
    {
      "ItemName": "",
      "Price": "",
      "Tier": "IV",
      "GearScore": "",
      "Availability": "1",
      "Location": ""
    },
    {
      "ItemName": "",
      "Price": "",
      "Tier": "",
      "GearScore": "7  17 77",
      "Availability": "170",
      "Location": ""
    },
    {
      "ItemName": "",
      "Price": "",
      "Tier": "",
      "GearScore": "7",
      "Availability": "1 1",
      "Location": ""
    },
    {
      "ItemName": "",
      "Price": "",
      "Tier": "",
      "GearScore": "7",
      "Availability": "4",
      "Location": ""
    },
    {
      "ItemName": "",
      "Price": "",
      "Tier": "",
      "GearScore": "7",
      "Availability": "2 1 1",
      "Location": ""
    },
    {
      "ItemName": "",
      "Price": "",
      "Tier": "",
      "GearScore": "",
      "Availability": "01 1",
      "Location": "Dttt A"
    },
    {
      "ItemName": "",
      "Price": "",
      "Tier": "",
      "GearScore": "",
      "Availability": "1",
      "Location": ""
    },
    {
      "ItemName": "",
      "Price": "",
      "Tier": "",
      "GearScore": "7",
      "Availability": "1 1",
      "Location": "e"
    },
    {
      "ItemName": "",
      "Price": "",
      "Tier": "",
      "GearScore": "7",
      "Availability": "0",
      "Location": ""
    },
    {
      "ItemName": "",
      "Price": "",
      "Tier": "",
      "GearScore": "7",
      "Availability": "1",
      "Location": ""
    },
    {
      "ItemName": "",
      "Price": "",
      "Tier": "",
      "GearScore": "2",
      "Availability": "4",
      "Location": "e T"
    },
    {
      "ItemName": "",
      "Price": "",
      "Tier": "",
      "GearScore": "7",
      "Availability": "",
      "Location": ""
    },
    {
      "ItemName": "Fire Mote",
      "Price": "13",
      "Tier": "II",
      "GearScore": "7",
      "Availability": "62",
      "Location": "Brightwood"
    },
    {
      "ItemName": "Fire Mote",
      "Price": "14",
      "Tier": "",
      "GearScore": "7",
      "Availability": "611",
      "Location": "First Light"
    },
    {
      "ItemName": "",
      "Price": "",
      "Tier": "",
      "GearScore": "3",
      "Availability": "401",
      "Location": "e"
    },
    {
      "ItemName": "",
      "Price": "",
      "Tier": "",
      "GearScore": "7",
      "Availability": "1 1 1",
      "Location": ""
    },
    {
      "ItemName": "",
      "Price": "",
      "Tier": "",
      "GearScore": "",
      "Availability": "",
      "Location": ""
    },
    {
      "ItemName": "",
      "Price": "",
      "Tier": "",
      "GearScore": "",
      "Availability": "101",
      "Location": ""
    },
    {
      "ItemName": "",
      "Price": "",
      "Tier": "",
      "GearScore": "",
      "Availability": "04",
      "Location": ""
    },
    {
      "ItemName": "",
      "Price": "",
      "Tier": "",
      "GearScore": "7",
      "Availability": "047",
      "Location": ""
    },
    {
      "ItemName": "",
      "Price": "",
      "Tier": "",
      "GearScore": "7",
      "Availability": "4 1",
      "Location": ""
    },
    {
      "ItemName": "",
      "Price": "",
      "Tier": "",
      "GearScore": "7",
      "Availability": "17",
      "Location": ""
    },
    {
      "ItemName": "",
      "Price": "",
      "Tier": "",
      "GearScore": "7",
      "Availability": "4 717",
      "Location": ""
    },
    {
      "ItemName": "Earth Mote",
      "Price": "",
      "Tier": "II",
      "GearScore": "7",
      "Availability": "119",
      "Location": "First Light"
    },
    {
      "ItemName": "",
      "Price": "",
      "Tier": "",
      "GearScore": "7",
      "Availability": "1101",
      "Location": "Syt bt"
    },
    {
      "ItemName": "",
      "Price": "",
      "Tier": "",
      "GearScore": "",
      "Availability": "114",
      "Location": ""
    },
    {
      "ItemName": "",
      "Price": "",
      "Tier": "",
      "GearScore": "",
      "Availability": "10",
      "Location": ""
    },
    {
      "ItemName": "",
      "Price": "",
      "Tier": "",
      "GearScore": "",
      "Availability": "1",
      "Location": "ST"
    },
    {
      "ItemName": "",
      "Price": "14511",
      "Tier": "",
      "GearScore": "7",
      "Availability": "00",
      "Location": ""
    },
    {
      "ItemName": "",
      "Price": "",
      "Tier": "",
      "GearScore": "7",
      "Availability": "10",
      "Location": "Dttt A"
    },
    {
      "ItemName": "",
      "Price": "",
      "Tier": "",
      "GearScore": "7",
      "Availability": "1",
      "Location": ""
    },
    {
      "ItemName": "",
      "Price": "",
      "Tier": "",
      "GearScore": "7",
      "Availability": "1",
      "Location": ""
    },
    {
      "ItemName": "",
      "Price": "",
      "Tier": "",
      "GearScore": "7",
      "Availability": "1",
      "Location": ""
    },
    {
      "ItemName": "Air Mote",
      "Price": "22",
      "Tier": "II",
      "GearScore": "7",
      "Availability": "1000",
      "Location": "Monarch's Bluffs"
    },
    {
      "ItemName": "",
      "Price": "1451",
      "Tier": "",
      "GearScore": "7",
      "Availability": "11",
      "Location": "ke’"
    },
    {
      "ItemName": "",
      "Price": "",
      "Tier": "",
      "GearScore": "",
      "Availability": "1",
      "Location": "Dttt A"
    },
    {
      "ItemName": "",
      "Price": "",
      "Tier": "",
      "GearScore": "",
      "Availability": "1  0",
      "Location": ""
    },
    {
      "ItemName": "",
      "Price": "",
      "Tier": "",
      "GearScore": "",
      "Availability": "1 1",
      "Location": ""
    },
    {
      "ItemName": "",
      "Price": "",
      "Tier": "",
      "GearScore": "7",
      "Availability": "4",
      "Location": ""
    },
    {
      "ItemName": "",
      "Price": "",
      "Tier": "",
      "GearScore": "7",
      "Availability": "141",
      "Location": ""
    },
    {
      "ItemName": "",
      "Price": "",
      "Tier": "",
      "GearScore": "",
      "Availability": "1",
      "Location": ""
    },
    {
      "ItemName": "",
      "Price": "",
      "Tier": "",
      "GearScore": "7  5 7",
      "Availability": "11",
      "Location": ""
    },
    {
      "ItemName": "",
      "Price": "",
      "Tier": "",
      "GearScore": "7",
      "Availability": "",
      "Location": "e TR"
    },
    {
      "ItemName": "",
      "Price": "1451",
      "Tier": "",
      "GearScore": "2",
      "Availability": "11",
      "Location": "i e"
    },
    {
      "ItemName": "",
      "Price": "",
      "Tier": "IIV",
      "GearScore": "",
      "Availability": "",
      "Location": "Dt A"
    },
    {
      "ItemName": "",
      "Price": "",
      "Tier": "",
      "GearScore": "",
      "Availability": "1  0",
      "Location": ""
    },
    {
      "ItemName": "",
      "Price": "",
      "Tier": "",
      "GearScore": "",
      "Availability": "1 1",
      "Location": ""
    },
    {
      "ItemName": "",
      "Price": "",
      "Tier": "",
      "GearScore": "7",
      "Availability": "4",
      "Location": ""
    },
    {
      "ItemName": "",
      "Price": "",
      "Tier": "",
      "GearScore": "7",
      "Availability": "141",
      "Location": ""
    },
    {
      "ItemName": "",
      "Price": "",
      "Tier": "",
      "GearScore": "7",
      "Availability": "1",
      "Location": ""
    },
    {
      "ItemName": "",
      "Price": "",
      "Tier": "",
      "GearScore": "7",
      "Availability": "11",
      "Location": ""
    },
    {
      "ItemName": "",
      "Price": "",
      "Tier": "",
      "GearScore": "7",
      "Availability": "",
      "Location": "e TR"
    },
    {
      "ItemName": "",
      "Price": "",
      "Tier": "",
      "GearScore": "",
      "Availability": "",
      "Location": ""
    },
    {
      "ItemName": "",
      "Price": "",
      "Tier": "",
      "GearScore": "2",
      "Availability": "",
      "Location": ""
    },
    {
      "ItemName": "",
      "Price": "",
      "Tier": "",
      "GearScore": "",
      "Availability": "",
      "Location": ""
    },
    {
      "ItemName": "",
      "Price": "",
      "Tier": "",
      "GearScore": "9",
      "Availability": "",
      "Location": ""
    },
    {
      "ItemName": "",
      "Price": "",
      "Tier": "",
      "GearScore": "",
      "Availability": "",
      "Location": ""
    },
    {
      "ItemName": "",
      "Price": "",
      "Tier": "",
      "GearScore": "",
      "Availability": "",
      "Location": ""
    },
    {
      "ItemName": "",
      "Price": "",
      "Tier": "",
      "GearScore": "5",
      "Availability": "",
      "Location": ""
    },
    {
      "ItemName": "",
      "Price": "",
      "Tier": "",
      "GearScore": "",
      "Availability": "",
      "Location": ""
    },
    {
      "ItemName": "",
      "Price": "",
      "Tier": "",
      "GearScore": "",
      "Availability": "1",
      "Location": ""
    },
    {
      "ItemName": "",
      "Price": "",
      "Tier": "",
      "GearScore": "",
      "Availability": "5",
      "Location": ""
    },
    {
      "ItemName": "Water Mote",
      "Price": "14",
      "Tier": "II",
      "GearScore": "",
      "Availability": "88",
      "Location": "Everfall"
    },
    {
      "ItemName": "Water Mote",
      "Price": "14",
      "Tier": "II",
      "GearScore": "",
      "Availability": "306",
      "Location": "Reekwater"
    },
    {
      "ItemName": "",
      "Price": "",
      "Tier": "",
      "GearScore": "2",
      "Availability": "5 1  1",
      "Location": ""
    },
    {
      "ItemName": "",
      "Price": "",
      "Tier": "",
      "GearScore": "",
      "Availability": "1",
      "Location": ""
    },
    {
      "ItemName": "",
      "Price": "",
      "Tier": "",
      "GearScore": "",
      "Availability": "001",
      "Location": ""
    },
    {
      "ItemName": "",
      "Price": "",
      "Tier": "",
      "GearScore": "",
      "Availability": "12",
      "Location": ""
    },
    {
      "ItemName": "",
      "Price": "",
      "Tier": "",
      "GearScore": "7",
      "Availability": "11   3",
      "Location": ""
    },
    {
      "ItemName": "",
      "Price": "",
      "Tier": "",
      "GearScore": "7",
      "Availability": "0 1",
      "Location": ""
    },
    {
      "ItemName": "",
      "Price": "",
      "Tier": "",
      "GearScore": "7",
      "Availability": "2",
      "Location": ""
    },
    {
      "ItemName": "",
      "Price": "",
      "Tier": "",
      "GearScore": "7",
      "Availability": "00",
      "Location": ""
    },
    {
      "ItemName": "",
      "Price": "",
      "Tier": "",
      "GearScore": "7",
      "Availability": "1 1 1",
      "Location": ""
    },
    {
      "ItemName": "",
      "Price": "",
      "Tier": "",
      "GearScore": "9",
      "Availability": "",
      "Location": ""
    },
    {
      "ItemName": "",
      "Price": "",
      "Tier": "",
      "GearScore": "1 314",
      "Availability": "",
      "Location": ""
    },
    {
      "ItemName": "",
      "Price": "",
      "Tier": "",
      "GearScore": "141   7 5  1  2",
      "Availability": "",
      "Location": ""
    },
    {
      "ItemName": "",
      "Price": "",
      "Tier": "",
      "GearScore": "",
      "Availability": "3",
      "Location": ""
    }
  ]
}